lava_lyra/__init__.py
lava_lyra/compat.py
lava_lyra/enums.py
lava_lyra/events.py
lava_lyra/exceptions.py
lava_lyra/filters.py
lava_lyra/lyrics.py
lava_lyra/objects.py
lava_lyra/player.py
lava_lyra/pool.py
lava_lyra/py.typed
lava_lyra/routeplanner.py
lava_lyra/search.py
lava_lyra/trackqueue.py
lava_lyra/utils.py
lava_lyra-1.6.0.dist-info/licenses/LICENSE
lava_lyra-1.6.0.dist-info/METADATA
lava_lyra-1.6.0.dist-info/WHEEL
lava_lyra-1.6.0.dist-info/top_level.txt
lava_lyra-1.6.0.dist-info/RECORD
