Metadata-Version: 2.4
Name: lava-lyra
Version: 1.6.0
Summary: A modern Lavalink v4 wrapper for py-cord, based on Pomice
Home-page: https://github.com/ParrotXray/lava-lyra
Author: ParrotXray
Author-email: 
License: GPL-3.0
Project-URL: Homepage, https://github.com/ParrotXray/lava-lyra
Project-URL: Repository, https://github.com/ParrotXray/lava-lyra
Project-URL: Issue Tracker, https://github.com/ParrotXray/lava-lyra/issues
Project-URL: Source, https://github.com/ParrotXray/lava-lyra
Project-URL: Changelog, https://github.com/ParrotXray/lava-lyra/blob/main/CHANGELOG.md
Project-URL: Original Pomice, https://github.com/cloudwithax/pomice
Keywords: discord,lavalink,py-cord,music,audio,lavalink4,voice,streaming
Classifier: Development Status :: 5 - Production/Stable
Classifier: Framework :: AsyncIO
Classifier: Intended Audience :: Developers
Classifier: License :: OSI Approved :: GNU General Public License v3 (GPLv3)
Classifier: Natural Language :: English
Classifier: Operating System :: OS Independent
Classifier: Programming Language :: Python
Classifier: Programming Language :: Python :: 3
Classifier: Programming Language :: Python :: 3 :: Only
Classifier: Programming Language :: Python :: 3.10
Classifier: Programming Language :: Python :: 3.11
Classifier: Programming Language :: Python :: 3.12
Classifier: Programming Language :: Python :: 3.13
Classifier: Programming Language :: Python :: Implementation :: CPython
Classifier: Topic :: Communications
Classifier: Topic :: Communications :: Chat
Classifier: Topic :: Internet
Classifier: Topic :: Multimedia :: Sound/Audio
Classifier: Topic :: Software Development
Classifier: Topic :: Software Development :: Libraries
Classifier: Topic :: Software Development :: Libraries :: Python Modules
Classifier: Topic :: System :: Networking
Classifier: Typing :: Typed
Requires-Python: >=3.10
License-File: LICENSE
Requires-Dist: aiohttp>=3.8.0
Requires-Dist: orjson>=3.8.0
Requires-Dist: websockets>=10.0
Requires-Dist: typing-extensions; python_version < "3.11"
Provides-Extra: pycord
Requires-Dist: py-cord>=2.6.0; extra == "pycord"
Provides-Extra: discordpy
Requires-Dist: discord.py>=2.6.0; extra == "discordpy"
Provides-Extra: docs
Requires-Dist: sphinx>=5.0.0; extra == "docs"
Requires-Dist: sphinx-rtd-theme>=1.0.0; extra == "docs"
Requires-Dist: sphinxcontrib-asyncio>=0.3.0; extra == "docs"
Provides-Extra: dev
Requires-Dist: pytest>=7.0.0; extra == "dev"
Requires-Dist: pytest-asyncio>=0.20.0; extra == "dev"
Requires-Dist: mypy>=0.991; extra == "dev"
Requires-Dist: black>=22.0.0; extra == "dev"
Requires-Dist: isort>=5.10.0; extra == "dev"
Requires-Dist: flake8>=5.0.0; extra == "dev"
Requires-Dist: pre-commit>=2.20.0; extra == "dev"
Provides-Extra: speed
Requires-Dist: aiohttp[speedups]; extra == "speed"
Requires-Dist: cchardet; extra == "speed"
Requires-Dist: aiodns; extra == "speed"
Requires-Dist: orjson; extra == "speed"
Dynamic: home-page
Dynamic: license-file
Dynamic: requires-python
